mempro/Insane4MemPrO.py
mempro/MemPrO.py
mempro/MemPrO_Script.py
mempro/__init__.py
mempro-0.0.10.dist-info/licenses/LICENSE
mempro-0.0.10.dist-info/METADATA
mempro-0.0.10.dist-info/WHEEL
mempro-0.0.10.dist-info/entry_points.txt
mempro-0.0.10.dist-info/top_level.txt
mempro-0.0.10.dist-info/RECORD
