Metadata-Version: 2.4
Name: mempro
Version: 0.0.10
Summary: A program for the orientation of membrane proteins and a coarse grained system builder based on INSANE
Author-email: Matyas Parrag <matyas.parrag@gmail.com>
License-Expression: GPL-3.0
Project-URL: Homepage, https://github.com/ShufflerBardOnTheEdge/MemPrO
Project-URL: Issues, https://github.com/ShufflerBardOnTheEdge/MemPrO/issues
Classifier: Programming Language :: Python :: 3
Requires-Python: >=3.11
License-File: LICENSE
Requires-Dist: argparse>=1.4.0
Requires-Dist: jax[cpu]<0.6.1,>=0.4.30
Requires-Dist: matplotlib>=3.8.4
Dynamic: license-file
